[
  {
    "name": "Quotes",
    "repo": "logicalgraphs/crypto-n-rust",
    "status": "success",
    "ran_at": "2026-06-29T07:15:00Z"
  },
  {
    "name": "Assets",
    "repo": "pivoteur/pivoteur.github.io",
    "status": "success",
    "ran_at": "2026-06-29T09:26:36Z"
  },
  {
    "name": "Virtsz",
    "repo": "pivoteur/pivoteur.github.io",
    "status": "success",
    "ran_at": "2026-06-29T08:45:06Z"
  },
  {
    "name": "Dusk",
    "repo": "pivoteur/pivoteur.github.io",
    "status": "success",
    "ran_at": "2026-06-28T10:33:14Z"
  },
  {
    "name": "Hwaet",
    "repo": "pivoteur/pivoteur.github.io",
    "status": "failure",
    "ran_at": "2026-06-28T10:55:59Z"
  },
  {
    "name": "R.A.T.",
    "repo": "pivoteur/protocol",
    "status": "success",
    "ran_at": "2026-06-29T06:12:58Z"
  }
]
